nog642_util/__init__.py
nog642_util-0.2.2.dist-info/METADATA
nog642_util-0.2.2.dist-info/WHEEL
nog642_util-0.2.2.dist-info/top_level.txt
nog642_util-0.2.2.dist-info/RECORD
